chainlogger/__init__.py
chainlogger/contract.py
chainlogger/hasher.py
chainlogger/logger.py
chainlogger/parser_class.py
chainlogger-0.0.3.dist-info/LICENSE
chainlogger-0.0.3.dist-info/METADATA
chainlogger-0.0.3.dist-info/WHEEL
chainlogger-0.0.3.dist-info/top_level.txt
chainlogger-0.0.3.dist-info/RECORD
