Metadata-Version: 2.1
Name: chainlogger
Version: 0.0.3
Summary: Log data into blockchain
Home-page: https://github.com/Open-Money/chainlogger-python
Author: MERT YILMAZ
Author-email: <mert@omlira.com>
License: UNKNOWN
Keywords: python,blockchain,logging
Platform: UNKNOWN
Classifier: Intended Audience :: Developers
Classifier: Programming Language :: Python :: 3
License-File: LICENSE
Requires-Dist: web3
